const aaload: u8 = 0x32;
const aastore: u8 = 0x53;
const aconst_null: u8 = 0x01;
const aload: u8 = 0x19;
const aload_0: u8 = 0x2a;
const aload_1: u8 = 0x2b;
const aload_2: u8 = 0x2c;
const aload_3: u8 = 0x2d;
const anewarray: u8 = 0xbd;
const areturn: u8 = 0xb0;
const arraylength: u8 = 0xbe;
const astore: u8 = 0x3a;
const astore_0: u8 = 0x4b;
const astore_1: u8 = 0x4c;
const astore_2: u8 = 0x4d;
const astore_3: u8 = 0x4e;
const athrow: u8 = 0xbf;
const baload: u8 = 0x33;
const bastore: u8 = 0x54;
const bipush: u8 = 0x10;
const caload: u8 = 0x34;
const castore: u8 = 0x55;
const checkcast: u8 = 0xc0;
const d2f: u8 = 0x90;
const d2i: u8 = 0x8e;
const d2l: u8 = 0x8f;
const dadd: u8 = 0x63;
const daload: u8 = 0x31;
const dastore: u8 = 0x52;
const dcmpl: u8 = 0x97;
const dcmpg: u8 = 0x98;
const dconst_0: u8 = 0x0e;
const dconst_1: u8 = 0x0f;
const ddiv: u8 = 0x6f;
const dload: u8 = 0x18;
const dload_0: u8 = 0x26;
const dload_1: u8 = 0x27;
const dload_2: u8 = 0x28;
const dload_3: u8 = 0x29;
const dmul: u8 = 0x6b;
const dneg: u8 = 0x77;
const drem: u8 = 0x73;
const dreturn: u8 = 0xaf;
const dstore: u8 = 0x39;
const dstore_0: u8 = 0x47;
const dstore_1: u8 = 0x48;
const dstore_2: u8 = 0x49;
const dstore_3: u8 = 0x4a;
const dsub: u8 = 0x67;
const dup: u8 = 0x59;
const dup_x1: u8 = 0x5a;
const dup_x2: u8 = 0x5b;
const dup2: u8 = 0x5c;
const dup2_x1: u8 = 0x5d;
const dup2_x2: u8 = 0x5e;
const f2d: u8 = 0x8d;
const f2i: u8 = 0x8b;
const f2l: u8 = 0x8c;
const fadd: u8 = 0x62;
const faload: u8 = 0x30;
const fastore: u8 = 0x51;
const fcmpl: u8 = 0x95;
const fcmpg: u8 = 0x96;
const fconst_0: u8 = 0x0b;
const fconst_1: u8 = 0x0c;
const fconst_2: u8 = 0x0d;
const fdiv: u8 = 0x6e;
const fload: u8 = 0x17;
const fload_0: u8 = 0x22;
const fload_1: u8 = 0x23;
const fload_2: u8 = 0x24;
const fload_3: u8 = 0x25;
const fmul: u8 = 0x6a;
const fneg: u8 = 0x76;
const frem: u8 = 0x72;
const freturn: u8 = 0xae;
const fstore: u8 = 0x38;
const fstore_0: u8 = 0x43;
const fstore_1: u8 = 0x44;
const fstore_2: u8 = 0x45;
const fstore_3: u8 = 0x46;
const fsub: u8 = 0x66;
const getfield: u8 = 0xb4;
const getstatic: u8 = 0xb2;
const goto: u8 = 0xa7;
const goto_w: u8 = 0xc8;
const i2b: u8 = 0x91;
const i2c: u8 = 0x92;
const i2d: u8 = 0x87;
const i2f: u8 = 0x86;
const i2l: u8 = 0x85;
const i2s: u8 = 0x93;
const iadd: u8 = 0x60;
const iaload: u8 = 0x2e;
const iand: u8 = 0x7e;
const iastore: u8 = 0x4f;
const iconst_m1: u8 = 0x2;
const iconst_0: u8 = 0x3;
const iconst_1: u8 = 0x4;
const iconst_2: u8 = 0x5;
const iconst_3: u8 = 0x6;
const iconst_4: u8 = 0x7;
const iconst_5: u8 = 0x8;
const idiv: u8 = 0x6c;
const if_acmpeq: u8 = 0xa5;
const if_acmpne: u8 = 0xa6;
const if_icmpeq: u8 = 0x9f;
const if_icmpne: u8 = 0xa0;
const if_icmplt: u8 = 0xa1;
const if_icmpge: u8 = 0xa2;
const if_icmpgt: u8 = 0xa3;
const if_icmple: u8 = 0xa4;
const ifeq: u8 = 0x99;
const ifne: u8 = 0x9a;
const iflt: u8 = 0x9b;
const ifge: u8 = 0x9c;
const ifgt: u8 = 0x9d;
const ifle: u8 = 0x9e;
const ifnull: u8 = 0xc6;
const ifnonnull: u8 = 0xc7;
const iinc: u8 = 0x84;
const iload: u8 = 0x15;
const iload_0: u8 = 0x1a;
const iload_1: u8 = 0x1b;
const iload_2: u8 = 0x1c;
const iload_3: u8 = 0x1d;
const imul: u8 = 0x68;
const ineg: u8 = 0x74;
const instanceof: u8 = 0xc1;
const invokedynamic: u8 = 0xba;
const invokeinterface: u8 = 0xb9;
const invokespecial: u8 = 0xb7;
const invokestatic: u8 = 0xb8;
const invokevirtual: u8 = 0xb6;
const ior: u8 = 0x80;
const irem: u8 = 0x70;
const ireturn: u8 = 0xac;
const ishl: u8 = 0x78;
const ishr: u8 = 0x7a;
const istore: u8 = 0x36;
const istore_0: u8 = 0x3b;
const istore_1: u8 = 0x3c;
const istore_2: u8 = 0x3d;
const istore_3: u8 = 0x3e;
const isub: u8 = 0x64;
const iushr: u8 = 0x7c;
const ixor: u8 = 0x82;
const jsr: u8 = 0xa8;
const jsr_w: u8 = 0xc9;
const l2d: u8 = 0x8a;
const l2f: u8 = 0x89;
const l2i: u8 = 0x88;
const ladd: u8 = 0x61;
const laload: u8 = 0x2f;
const land: u8 = 0x7f;
const lastore: u8 = 0x50;
const lcmp: u8 = 0x94;
const lconst_0: u8 = 0x09;
const lconst_1: u8 = 0x0a;
const ldc: u8 = 0x12;
const ldc_w: u8 = 0x13;
const ldc2_w: u8 = 0x14;
const ldiv: u8 = 0x6d;
const lload: u8 = 0x16;
const lload_0: u8 = 0x1e;
const lload_1: u8 = 0x1f;
const lload_2: u8 = 0x20;
const lload_3: u8 = 0x21;
const lmul: u8 = 0x69;
const lneg: u8 = 0x75;
const lookupswitch: u8 = 0xab;
const lor: u8 = 0x81;
const lrem: u8 = 0x71;
const lreturn: u8 = 0xad;
const lshl: u8 = 0x79;
const lshr: u8 = 0x7b;
const lstore: u8 = 0x37;
const lstore_0: u8 = 0x3f;
const lstore_1: u8 = 0x40;
const lstore_2: u8 = 0x41;
const lstore_3: u8 = 0x42;
const lsub: u8 = 0x65;
const lushr: u8 = 0x7d;
const lxor: u8 = 0x83;
const monitorenter: u8 = 0xc2;
const monitorexit: u8 = 0xc3;
const multianewarray: u8 = 0xc5;
const new: u8 = 0xbb;
const newarray: u8 = 0xbc;
const nop: u8 = 0;
const pop: u8 = 0x57;
const pop2: u8 = 0x58;
const putfield: u8 = 0xb5;
const putstatic: u8 = 0xb3;
const ret: u8 = 0xa9;
const retv: u8 = 0xb1;
const saload: u8 = 0x35;
const sastore: u8 = 0x56;
const sipush: u8 = 0x11;
const swap: u8 = 0x5f;
const tableswitch: u8 = 0xaa;
const wide: u8 = 0xc4;
